autocuda/__init__.py
autocuda/autocuda.py
autocuda-0.16.dist-info/LICENSE
autocuda-0.16.dist-info/METADATA
autocuda-0.16.dist-info/WHEEL
autocuda-0.16.dist-info/top_level.txt
autocuda-0.16.dist-info/RECORD
